{"id":157192,"title":{"english":"[Senbon Knock Zadankai (Inaba Fuyuki)] Ikazuchi-chan ga Takusan no Shireikan to Juukon Shite Yasen de Hustle Suru Hon (Kantai Collection -KanColle-) [Digital]","japanese":"[千本ノック座談会 (稲場冬樹)] 雷ちゃんがたくさんのしれーかんとジュウコンして夜戦でハッスルする本 (艦隊これくしょん -艦これ-) [DL版]","display":"Ikazuchi-chan ga Takusan no Shireikan to Juukon Shite Yasen de Hustle Suru Hon"},"images":{"cover":{"link":"https://i.nhentai.net/galleries/905908/cover.jpg","info":{"width":350,"height":494,"type":"jpg"}},"thumbnail":{"link":"https://i.nhentai.net/galleries/905908/cover.jpg","info":{"width":250,"height":353,"type":"jpg"}},"pages":[{"link":"https://i.nhentai.net/galleries/905908/1.jpg","info":{"width":250,"height":353,"type":"jpg"}},{"link":"https://i.nhentai.net/galleries/905908/2.jpg","info":{"width":250,"height":353,"type":"jpg"}},{"link":"https://i.nhentai.net/galleries/905908/3.jpg","info":{"width":250,"height":353,"type":"jpg"}},{"link":"https://i.nhentai.net/galleries/905908/4.jpg","info":{"width":250,"height":353,"type":"jpg"}},{"link":"https://i.nhentai.net/galleries/905908/5.jpg","info":{"width":250,"height":353,"type":"jpg"}},{"link":"https://i.nhentai.net/galleries/905908/6.jpg","info":{"width":250,"height":353,"type":"jpg"}},{"link":"https://i.nhentai.net/galleries/905908/7.jpg","info":{"width":250,"height":353,"type":"jpg"}},{"link":"https://i.nhentai.net/galleries/905908/8.jpg","info":{"width":250,"height":353,"type":"jpg"}},{"link":"https://i.nhentai.net/galleries/905908/9.jpg","info":{"width":250,"height":353,"type":"jpg"}},{"link":"https://i.nhentai.net/galleries/905908/10.jpg","info":{"width":250,"height":353,"type":"jpg"}},{"link":"https://i.nhentai.net/galleries/905908/11.jpg","info":{"width":250,"height":353,"type":"jpg"}},{"link":"https://i.nhentai.net/galleries/905908/12.jpg","info":{"width":250,"height":353,"type":"jpg"}},{"link":"https://i.nhentai.net/galleries/905908/13.jpg","info":{"width":250,"height":353,"type":"jpg"}},{"link":"https://i.nhentai.net/galleries/905908/14.jpg","info":{"width":250,"height":353,"type":"jpg"}},{"link":"https://i.nhentai.net/galleries/905908/15.jpg","info":{"width":250,"height":353,"type":"jpg"}},{"link":"https://i.nhentai.net/galleries/905908/16.jpg","info":{"width":250,"height":353,"type":"jpg"}},{"link":"https://i.nhentai.net/galleries/905908/17.jpg","info":{"width":250,"height":353,"type":"jpg"}},{"link":"https://i.nhentai.net/galleries/905908/18.jpg","info":{"width":250,"height":353,"type":"jpg"}},{"link":"https://i.nhentai.net/galleries/905908/19.jpg","info":{"width":250,"height":353,"type":"jpg"}},{"link":"https://i.nhentai.net/galleries/905908/20.jpg","info":{"width":250,"height":353,"type":"jpg"}},{"link":"https://i.nhentai.net/galleries/905908/21.jpg","info":{"width":250,"height":353,"type":"jpg"}},{"link":"https://i.nhentai.net/galleries/905908/22.jpg","info":{"width":250,"height":353,"type":"jpg"}},{"link":"https://i.nhentai.net/galleries/905908/23.jpg","info":{"width":250,"height":353,"type":"jpg"}},{"link":"https://i.nhentai.net/galleries/905908/24.jpg","info":{"width":250,"height":353,"type":"jpg"}},{"link":"https://i.nhentai.net/galleries/905908/25.jpg","info":{"width":250,"height":353,"type":"jpg"}},{"link":"https://i.nhentai.net/galleries/905908/26.jpg","info":{"width":250,"height":353,"type":"jpg"}},{"link":"https://i.nhentai.net/galleries/905908/27.jpg","info":{"width":250,"height":353,"type":"jpg"}},{"link":"https://i.nhentai.net/galleries/905908/28.jpg","info":{"width":250,"height":353,"type":"jpg"}}]},"info":{"amount":28,"mediaId":905908},"metadata":{"artists":[{"name":"inaba fuyuki","count":56}],"categories":[{"name":"doujinshi","count":228729}],"characters":[{"name":"ikazuchi","count":327}],"groups":[{"name":"senbon knock zadankai","count":63}],"language":"japanese","parodies":[{"name":"kantai collection","count":13889}],"tags":[{"name":"group","count":72150},{"name":"mmf threesome","count":9810},{"name":"anal","count":64587},{"name":"double penetration","count":24673},{"name":"femdom","count":17603},{"name":"lolicon","count":69490},{"name":"rimjob","count":4223},{"name":"stockings","count":64784},{"name":"strap-on","count":4060},{"name":"x-ray","count":21189},{"name":"prostate massage","count":2331},{"name":"pegging","count":1939},{"name":"nakadashi","count":42357}]}}