{"id":200318,"title":{"english":"[Hi-Per Pinch (clover)] N - Zenra Seikatsu (IS &lt;Infinite Stratos&gt;) [Digital]","japanese":"[ハイパーピンチ (clover)] N エヌ-全裸生活 (IS＜インフィニット・ストラトス＞) [DL版]","display":"N - Zenra Seikatsu"},"images":{"cover":{"link":"https://t.nhentai.net/galleries/1084319/cover.jpg","info":{"width":350,"height":494,"type":"jpg"}},"thumbnail":{"link":"https://t.nhentai.net/galleries/1084319/1t.jpg","info":{"width":250,"height":353,"type":"jpg"}},"pages":[{"link":"https://i.nhentai.net/galleries/1084319/1.jpg","info":{"width":250,"height":353,"type":"jpg"}},{"link":"https://i.nhentai.net/galleries/1084319/2.jpg","info":{"width":250,"height":353,"type":"jpg"}},{"link":"https://i.nhentai.net/galleries/1084319/3.jpg","info":{"width":250,"height":353,"type":"jpg"}},{"link":"https://i.nhentai.net/galleries/1084319/4.jpg","info":{"width":250,"height":353,"type":"jpg"}},{"link":"https://i.nhentai.net/galleries/1084319/5.jpg","info":{"width":250,"height":353,"type":"jpg"}},{"link":"https://i.nhentai.net/galleries/1084319/6.jpg","info":{"width":250,"height":353,"type":"jpg"}},{"link":"https://i.nhentai.net/galleries/1084319/7.jpg","info":{"width":250,"height":353,"type":"jpg"}},{"link":"https://i.nhentai.net/galleries/1084319/8.jpg","info":{"width":250,"height":353,"type":"jpg"}},{"link":"https://i.nhentai.net/galleries/1084319/9.jpg","info":{"width":250,"height":353,"type":"jpg"}},{"link":"https://i.nhentai.net/galleries/1084319/10.jpg","info":{"width":250,"height":353,"type":"jpg"}},{"link":"https://i.nhentai.net/galleries/1084319/11.jpg","info":{"width":250,"height":353,"type":"jpg"}},{"link":"https://i.nhentai.net/galleries/1084319/12.jpg","info":{"width":250,"height":353,"type":"jpg"}},{"link":"https://i.nhentai.net/galleries/1084319/13.jpg","info":{"width":250,"height":353,"type":"jpg"}},{"link":"https://i.nhentai.net/galleries/1084319/14.jpg","info":{"width":250,"height":353,"type":"jpg"}},{"link":"https://i.nhentai.net/galleries/1084319/15.jpg","info":{"width":250,"height":353,"type":"jpg"}},{"link":"https://i.nhentai.net/galleries/1084319/16.jpg","info":{"width":250,"height":353,"type":"jpg"}},{"link":"https://i.nhentai.net/galleries/1084319/17.jpg","info":{"width":250,"height":353,"type":"jpg"}},{"link":"https://i.nhentai.net/galleries/1084319/18.jpg","info":{"width":250,"height":353,"type":"jpg"}},{"link":"https://i.nhentai.net/galleries/1084319/19.jpg","info":{"width":250,"height":353,"type":"jpg"}},{"link":"https://i.nhentai.net/galleries/1084319/20.jpg","info":{"width":250,"height":353,"type":"jpg"}},{"link":"https://i.nhentai.net/galleries/1084319/21.jpg","info":{"width":250,"height":353,"type":"jpg"}},{"link":"https://i.nhentai.net/galleries/1084319/22.jpg","info":{"width":250,"height":353,"type":"jpg"}},{"link":"https://i.nhentai.net/galleries/1084319/23.jpg","info":{"width":250,"height":353,"type":"jpg"}},{"link":"https://i.nhentai.net/galleries/1084319/24.jpg","info":{"width":250,"height":353,"type":"jpg"}},{"link":"https://i.nhentai.net/galleries/1084319/25.jpg","info":{"width":250,"height":353,"type":"jpg"}},{"link":"https://i.nhentai.net/galleries/1084319/26.jpg","info":{"width":250,"height":353,"type":"jpg"}},{"link":"https://i.nhentai.net/galleries/1084319/27.jpg","info":{"width":250,"height":353,"type":"jpg"}},{"link":"https://i.nhentai.net/galleries/1084319/28.jpg","info":{"width":250,"height":353,"type":"jpg"}},{"link":"https://i.nhentai.net/galleries/1084319/29.jpg","info":{"width":250,"height":353,"type":"jpg"}},{"link":"https://i.nhentai.net/galleries/1084319/30.jpg","info":{"width":250,"height":353,"type":"jpg"}},{"link":"https://i.nhentai.net/galleries/1084319/31.jpg","info":{"width":250,"height":353,"type":"jpg"}},{"link":"https://i.nhentai.net/galleries/1084319/32.jpg","info":{"width":250,"height":353,"type":"jpg"}},{"link":"https://i.nhentai.net/galleries/1084319/33.jpg","info":{"width":250,"height":353,"type":"jpg"}},{"link":"https://i.nhentai.net/galleries/1084319/34.jpg","info":{"width":250,"height":353,"type":"jpg"}},{"link":"https://i.nhentai.net/galleries/1084319/35.jpg","info":{"width":250,"height":353,"type":"jpg"}},{"link":"https://i.nhentai.net/galleries/1084319/36.jpg","info":{"width":250,"height":353,"type":"jpg"}},{"link":"https://i.nhentai.net/galleries/1084319/37.jpg","info":{"width":250,"height":353,"type":"jpg"}},{"link":"https://i.nhentai.net/galleries/1084319/38.jpg","info":{"width":250,"height":353,"type":"jpg"}},{"link":"https://i.nhentai.net/galleries/1084319/39.jpg","info":{"width":250,"height":353,"type":"jpg"}}]},"info":{"amount":39,"mediaId":1084319,"upload":1499567570},"metadata":{"artists":["clover"],"categories":["doujinshi"],"characters":["cecilia alcott","charlotte dunois","ichika orimura"],"groups":["hi-per pinch"],"language":"japanese","parodies":["infinite stratos"],"tags":["ffm threesome","group","mosaic censorship","anal","big breasts","hairy","hairy armpits","impregnation","pregnant","scat","urination","x-ray","big penis","sole male","piss drinking"]}}