{"id":20190,"title":{"english":"[Iwabuchi Piroshi] Shiborizome Jounetsu Syrup","japanese":"[いわぶちぴろし] 搾り初め嬢熱シロップ","display":"Shiborizome Jounetsu Syrup"},"images":{"cover":{"link":"https://t.nhentai.net/galleries/73130/cover.jpg","info":{"width":350,"height":504,"type":"jpg"}},"thumbnail":{"link":"https://t.nhentai.net/galleries/73130/1t.jpg","info":{"width":250,"height":360,"type":"jpg"}},"pages":[{"link":"https://i.nhentai.net/galleries/73130/1.jpg","info":{"width":250,"height":360,"type":"jpg"}},{"link":"https://i.nhentai.net/galleries/73130/2.jpg","info":{"width":250,"height":360,"type":"jpg"}},{"link":"https://i.nhentai.net/galleries/73130/3.jpg","info":{"width":250,"height":360,"type":"jpg"}},{"link":"https://i.nhentai.net/galleries/73130/4.jpg","info":{"width":250,"height":360,"type":"jpg"}},{"link":"https://i.nhentai.net/galleries/73130/5.jpg","info":{"width":250,"height":360,"type":"jpg"}},{"link":"https://i.nhentai.net/galleries/73130/6.jpg","info":{"width":250,"height":360,"type":"jpg"}},{"link":"https://i.nhentai.net/galleries/73130/7.jpg","info":{"width":250,"height":360,"type":"jpg"}},{"link":"https://i.nhentai.net/galleries/73130/8.jpg","info":{"width":250,"height":360,"type":"jpg"}},{"link":"https://i.nhentai.net/galleries/73130/9.jpg","info":{"width":250,"height":360,"type":"jpg"}},{"link":"https://i.nhentai.net/galleries/73130/10.jpg","info":{"width":250,"height":360,"type":"jpg"}},{"link":"https://i.nhentai.net/galleries/73130/11.jpg","info":{"width":250,"height":360,"type":"jpg"}},{"link":"https://i.nhentai.net/galleries/73130/12.jpg","info":{"width":250,"height":360,"type":"jpg"}},{"link":"https://i.nhentai.net/galleries/73130/13.jpg","info":{"width":250,"height":360,"type":"jpg"}},{"link":"https://i.nhentai.net/galleries/73130/14.jpg","info":{"width":250,"height":360,"type":"jpg"}},{"link":"https://i.nhentai.net/galleries/73130/15.jpg","info":{"width":250,"height":360,"type":"jpg"}},{"link":"https://i.nhentai.net/galleries/73130/16.jpg","info":{"width":250,"height":360,"type":"jpg"}},{"link":"https://i.nhentai.net/galleries/73130/17.jpg","info":{"width":250,"height":360,"type":"jpg"}},{"link":"https://i.nhentai.net/galleries/73130/18.jpg","info":{"width":250,"height":360,"type":"jpg"}},{"link":"https://i.nhentai.net/galleries/73130/19.jpg","info":{"width":250,"height":360,"type":"jpg"}},{"link":"https://i.nhentai.net/galleries/73130/20.jpg","info":{"width":250,"height":360,"type":"jpg"}},{"link":"https://i.nhentai.net/galleries/73130/21.jpg","info":{"width":250,"height":360,"type":"jpg"}},{"link":"https://i.nhentai.net/galleries/73130/22.jpg","info":{"width":250,"height":360,"type":"jpg"}},{"link":"https://i.nhentai.net/galleries/73130/23.jpg","info":{"width":250,"height":360,"type":"jpg"}},{"link":"https://i.nhentai.net/galleries/73130/24.jpg","info":{"width":250,"height":360,"type":"jpg"}},{"link":"https://i.nhentai.net/galleries/73130/25.jpg","info":{"width":250,"height":360,"type":"jpg"}},{"link":"https://i.nhentai.net/galleries/73130/26.jpg","info":{"width":250,"height":360,"type":"jpg"}},{"link":"https://i.nhentai.net/galleries/73130/27.jpg","info":{"width":250,"height":360,"type":"jpg"}},{"link":"https://i.nhentai.net/galleries/73130/28.jpg","info":{"width":250,"height":360,"type":"jpg"}},{"link":"https://i.nhentai.net/galleries/73130/29.jpg","info":{"width":250,"height":360,"type":"jpg"}},{"link":"https://i.nhentai.net/galleries/73130/30.jpg","info":{"width":250,"height":360,"type":"jpg"}},{"link":"https://i.nhentai.net/galleries/73130/31.jpg","info":{"width":250,"height":360,"type":"jpg"}},{"link":"https://i.nhentai.net/galleries/73130/32.jpg","info":{"width":250,"height":360,"type":"jpg"}},{"link":"https://i.nhentai.net/galleries/73130/33.jpg","info":{"width":250,"height":360,"type":"jpg"}},{"link":"https://i.nhentai.net/galleries/73130/34.jpg","info":{"width":250,"height":360,"type":"jpg"}},{"link":"https://i.nhentai.net/galleries/73130/35.jpg","info":{"width":250,"height":360,"type":"jpg"}},{"link":"https://i.nhentai.net/galleries/73130/36.jpg","info":{"width":250,"height":360,"type":"jpg"}},{"link":"https://i.nhentai.net/galleries/73130/37.jpg","info":{"width":250,"height":360,"type":"jpg"}},{"link":"https://i.nhentai.net/galleries/73130/38.jpg","info":{"width":250,"height":360,"type":"jpg"}},{"link":"https://i.nhentai.net/galleries/73130/39.jpg","info":{"width":250,"height":360,"type":"jpg"}},{"link":"https://i.nhentai.net/galleries/73130/40.jpg","info":{"width":250,"height":360,"type":"jpg"}},{"link":"https://i.nhentai.net/galleries/73130/41.jpg","info":{"width":250,"height":360,"type":"jpg"}},{"link":"https://i.nhentai.net/galleries/73130/42.jpg","info":{"width":250,"height":360,"type":"jpg"}},{"link":"https://i.nhentai.net/galleries/73130/43.jpg","info":{"width":250,"height":360,"type":"jpg"}},{"link":"https://i.nhentai.net/galleries/73130/44.jpg","info":{"width":250,"height":360,"type":"jpg"}},{"link":"https://i.nhentai.net/galleries/73130/45.jpg","info":{"width":250,"height":360,"type":"jpg"}},{"link":"https://i.nhentai.net/galleries/73130/46.jpg","info":{"width":250,"height":360,"type":"jpg"}},{"link":"https://i.nhentai.net/galleries/73130/47.jpg","info":{"width":250,"height":360,"type":"jpg"}},{"link":"https://i.nhentai.net/galleries/73130/48.jpg","info":{"width":250,"height":360,"type":"jpg"}},{"link":"https://i.nhentai.net/galleries/73130/49.jpg","info":{"width":250,"height":360,"type":"jpg"}},{"link":"https://i.nhentai.net/galleries/73130/50.jpg","info":{"width":250,"height":360,"type":"jpg"}},{"link":"https://i.nhentai.net/galleries/73130/51.jpg","info":{"width":250,"height":360,"type":"jpg"}},{"link":"https://i.nhentai.net/galleries/73130/52.jpg","info":{"width":250,"height":360,"type":"jpg"}},{"link":"https://i.nhentai.net/galleries/73130/53.jpg","info":{"width":250,"height":360,"type":"jpg"}},{"link":"https://i.nhentai.net/galleries/73130/54.jpg","info":{"width":250,"height":360,"type":"jpg"}},{"link":"https://i.nhentai.net/galleries/73130/55.jpg","info":{"width":250,"height":360,"type":"jpg"}},{"link":"https://i.nhentai.net/galleries/73130/56.jpg","info":{"width":250,"height":360,"type":"jpg"}},{"link":"https://i.nhentai.net/galleries/73130/57.jpg","info":{"width":250,"height":360,"type":"jpg"}},{"link":"https://i.nhentai.net/galleries/73130/58.jpg","info":{"width":250,"height":360,"type":"jpg"}},{"link":"https://i.nhentai.net/galleries/73130/59.jpg","info":{"width":250,"height":360,"type":"jpg"}},{"link":"https://i.nhentai.net/galleries/73130/60.jpg","info":{"width":250,"height":360,"type":"jpg"}},{"link":"https://i.nhentai.net/galleries/73130/61.jpg","info":{"width":250,"height":360,"type":"jpg"}},{"link":"https://i.nhentai.net/galleries/73130/62.jpg","info":{"width":250,"height":360,"type":"jpg"}},{"link":"https://i.nhentai.net/galleries/73130/63.jpg","info":{"width":250,"height":360,"type":"jpg"}},{"link":"https://i.nhentai.net/galleries/73130/64.jpg","info":{"width":250,"height":360,"type":"jpg"}},{"link":"https://i.nhentai.net/galleries/73130/65.jpg","info":{"width":250,"height":360,"type":"jpg"}},{"link":"https://i.nhentai.net/galleries/73130/66.jpg","info":{"width":250,"height":360,"type":"jpg"}},{"link":"https://i.nhentai.net/galleries/73130/67.jpg","info":{"width":250,"height":360,"type":"jpg"}},{"link":"https://i.nhentai.net/galleries/73130/68.jpg","info":{"width":250,"height":360,"type":"jpg"}},{"link":"https://i.nhentai.net/galleries/73130/69.jpg","info":{"width":250,"height":360,"type":"jpg"}},{"link":"https://i.nhentai.net/galleries/73130/70.jpg","info":{"width":250,"height":360,"type":"jpg"}},{"link":"https://i.nhentai.net/galleries/73130/71.jpg","info":{"width":250,"height":360,"type":"jpg"}},{"link":"https://i.nhentai.net/galleries/73130/72.jpg","info":{"width":250,"height":360,"type":"jpg"}},{"link":"https://i.nhentai.net/galleries/73130/73.jpg","info":{"width":250,"height":360,"type":"jpg"}},{"link":"https://i.nhentai.net/galleries/73130/74.jpg","info":{"width":250,"height":360,"type":"jpg"}},{"link":"https://i.nhentai.net/galleries/73130/75.jpg","info":{"width":250,"height":360,"type":"jpg"}},{"link":"https://i.nhentai.net/galleries/73130/76.jpg","info":{"width":250,"height":360,"type":"jpg"}},{"link":"https://i.nhentai.net/galleries/73130/77.jpg","info":{"width":250,"height":360,"type":"jpg"}},{"link":"https://i.nhentai.net/galleries/73130/78.jpg","info":{"width":250,"height":360,"type":"jpg"}},{"link":"https://i.nhentai.net/galleries/73130/79.jpg","info":{"width":250,"height":360,"type":"jpg"}},{"link":"https://i.nhentai.net/galleries/73130/80.jpg","info":{"width":250,"height":360,"type":"jpg"}},{"link":"https://i.nhentai.net/galleries/73130/81.jpg","info":{"width":250,"height":360,"type":"jpg"}},{"link":"https://i.nhentai.net/galleries/73130/82.jpg","info":{"width":250,"height":360,"type":"jpg"}},{"link":"https://i.nhentai.net/galleries/73130/83.jpg","info":{"width":250,"height":360,"type":"jpg"}},{"link":"https://i.nhentai.net/galleries/73130/84.jpg","info":{"width":250,"height":360,"type":"jpg"}},{"link":"https://i.nhentai.net/galleries/73130/85.jpg","info":{"width":250,"height":360,"type":"jpg"}},{"link":"https://i.nhentai.net/galleries/73130/86.jpg","info":{"width":250,"height":360,"type":"jpg"}},{"link":"https://i.nhentai.net/galleries/73130/87.jpg","info":{"width":250,"height":360,"type":"jpg"}},{"link":"https://i.nhentai.net/galleries/73130/88.jpg","info":{"width":250,"height":360,"type":"jpg"}},{"link":"https://i.nhentai.net/galleries/73130/89.jpg","info":{"width":250,"height":360,"type":"jpg"}},{"link":"https://i.nhentai.net/galleries/73130/90.jpg","info":{"width":250,"height":360,"type":"jpg"}},{"link":"https://i.nhentai.net/galleries/73130/91.jpg","info":{"width":250,"height":360,"type":"jpg"}},{"link":"https://i.nhentai.net/galleries/73130/92.jpg","info":{"width":250,"height":360,"type":"jpg"}},{"link":"https://i.nhentai.net/galleries/73130/93.jpg","info":{"width":250,"height":360,"type":"jpg"}},{"link":"https://i.nhentai.net/galleries/73130/94.jpg","info":{"width":250,"height":360,"type":"jpg"}},{"link":"https://i.nhentai.net/galleries/73130/95.jpg","info":{"width":250,"height":360,"type":"jpg"}},{"link":"https://i.nhentai.net/galleries/73130/96.jpg","info":{"width":250,"height":360,"type":"jpg"}},{"link":"https://i.nhentai.net/galleries/73130/97.jpg","info":{"width":250,"height":360,"type":"jpg"}},{"link":"https://i.nhentai.net/galleries/73130/98.jpg","info":{"width":250,"height":360,"type":"jpg"}},{"link":"https://i.nhentai.net/galleries/73130/99.jpg","info":{"width":250,"height":360,"type":"jpg"}},{"link":"https://i.nhentai.net/galleries/73130/100.jpg","info":{"width":250,"height":360,"type":"jpg"}},{"link":"https://i.nhentai.net/galleries/73130/101.jpg","info":{"width":250,"height":360,"type":"jpg"}},{"link":"https://i.nhentai.net/galleries/73130/102.jpg","info":{"width":250,"height":360,"type":"jpg"}},{"link":"https://i.nhentai.net/galleries/73130/103.jpg","info":{"width":250,"height":360,"type":"jpg"}},{"link":"https://i.nhentai.net/galleries/73130/104.jpg","info":{"width":250,"height":360,"type":"jpg"}},{"link":"https://i.nhentai.net/galleries/73130/105.jpg","info":{"width":250,"height":360,"type":"jpg"}},{"link":"https://i.nhentai.net/galleries/73130/106.jpg","info":{"width":250,"height":360,"type":"jpg"}},{"link":"https://i.nhentai.net/galleries/73130/107.jpg","info":{"width":250,"height":360,"type":"jpg"}},{"link":"https://i.nhentai.net/galleries/73130/108.jpg","info":{"width":250,"height":360,"type":"jpg"}},{"link":"https://i.nhentai.net/galleries/73130/109.jpg","info":{"width":250,"height":360,"type":"jpg"}},{"link":"https://i.nhentai.net/galleries/73130/110.jpg","info":{"width":250,"height":360,"type":"jpg"}},{"link":"https://i.nhentai.net/galleries/73130/111.jpg","info":{"width":250,"height":360,"type":"jpg"}},{"link":"https://i.nhentai.net/galleries/73130/112.jpg","info":{"width":250,"height":360,"type":"jpg"}},{"link":"https://i.nhentai.net/galleries/73130/113.jpg","info":{"width":250,"height":360,"type":"jpg"}},{"link":"https://i.nhentai.net/galleries/73130/114.jpg","info":{"width":250,"height":360,"type":"jpg"}},{"link":"https://i.nhentai.net/galleries/73130/115.jpg","info":{"width":250,"height":360,"type":"jpg"}},{"link":"https://i.nhentai.net/galleries/73130/116.jpg","info":{"width":250,"height":360,"type":"jpg"}},{"link":"https://i.nhentai.net/galleries/73130/117.jpg","info":{"width":250,"height":360,"type":"jpg"}},{"link":"https://i.nhentai.net/galleries/73130/118.jpg","info":{"width":250,"height":360,"type":"jpg"}},{"link":"https://i.nhentai.net/galleries/73130/119.jpg","info":{"width":250,"height":360,"type":"jpg"}},{"link":"https://i.nhentai.net/galleries/73130/120.jpg","info":{"width":250,"height":360,"type":"jpg"}},{"link":"https://i.nhentai.net/galleries/73130/121.jpg","info":{"width":250,"height":360,"type":"jpg"}},{"link":"https://i.nhentai.net/galleries/73130/122.jpg","info":{"width":250,"height":360,"type":"jpg"}},{"link":"https://i.nhentai.net/galleries/73130/123.jpg","info":{"width":250,"height":360,"type":"jpg"}},{"link":"https://i.nhentai.net/galleries/73130/124.jpg","info":{"width":250,"height":360,"type":"jpg"}},{"link":"https://i.nhentai.net/galleries/73130/125.jpg","info":{"width":250,"height":360,"type":"jpg"}},{"link":"https://i.nhentai.net/galleries/73130/126.jpg","info":{"width":250,"height":360,"type":"jpg"}},{"link":"https://i.nhentai.net/galleries/73130/127.jpg","info":{"width":250,"height":360,"type":"jpg"}},{"link":"https://i.nhentai.net/galleries/73130/128.jpg","info":{"width":250,"height":360,"type":"jpg"}},{"link":"https://i.nhentai.net/galleries/73130/129.jpg","info":{"width":250,"height":360,"type":"jpg"}},{"link":"https://i.nhentai.net/galleries/73130/130.jpg","info":{"width":250,"height":360,"type":"jpg"}},{"link":"https://i.nhentai.net/galleries/73130/131.jpg","info":{"width":250,"height":360,"type":"jpg"}},{"link":"https://i.nhentai.net/galleries/73130/132.jpg","info":{"width":250,"height":360,"type":"jpg"}},{"link":"https://i.nhentai.net/galleries/73130/133.jpg","info":{"width":250,"height":360,"type":"jpg"}},{"link":"https://i.nhentai.net/galleries/73130/134.jpg","info":{"width":250,"height":360,"type":"jpg"}},{"link":"https://i.nhentai.net/galleries/73130/135.jpg","info":{"width":250,"height":360,"type":"jpg"}},{"link":"https://i.nhentai.net/galleries/73130/136.jpg","info":{"width":250,"height":360,"type":"jpg"}},{"link":"https://i.nhentai.net/galleries/73130/137.jpg","info":{"width":250,"height":360,"type":"jpg"}},{"link":"https://i.nhentai.net/galleries/73130/138.jpg","info":{"width":250,"height":360,"type":"jpg"}},{"link":"https://i.nhentai.net/galleries/73130/139.jpg","info":{"width":250,"height":360,"type":"jpg"}},{"link":"https://i.nhentai.net/galleries/73130/140.jpg","info":{"width":250,"height":360,"type":"jpg"}},{"link":"https://i.nhentai.net/galleries/73130/141.jpg","info":{"width":250,"height":360,"type":"jpg"}},{"link":"https://i.nhentai.net/galleries/73130/142.jpg","info":{"width":250,"height":360,"type":"jpg"}},{"link":"https://i.nhentai.net/galleries/73130/143.jpg","info":{"width":250,"height":360,"type":"jpg"}},{"link":"https://i.nhentai.net/galleries/73130/144.jpg","info":{"width":250,"height":360,"type":"jpg"}},{"link":"https://i.nhentai.net/galleries/73130/145.jpg","info":{"width":250,"height":360,"type":"jpg"}},{"link":"https://i.nhentai.net/galleries/73130/146.jpg","info":{"width":250,"height":360,"type":"jpg"}},{"link":"https://i.nhentai.net/galleries/73130/147.jpg","info":{"width":250,"height":360,"type":"jpg"}},{"link":"https://i.nhentai.net/galleries/73130/148.jpg","info":{"width":250,"height":360,"type":"jpg"}},{"link":"https://i.nhentai.net/galleries/73130/149.jpg","info":{"width":250,"height":360,"type":"jpg"}},{"link":"https://i.nhentai.net/galleries/73130/150.jpg","info":{"width":250,"height":360,"type":"jpg"}},{"link":"https://i.nhentai.net/galleries/73130/151.jpg","info":{"width":250,"height":360,"type":"jpg"}},{"link":"https://i.nhentai.net/galleries/73130/152.jpg","info":{"width":250,"height":360,"type":"jpg"}},{"link":"https://i.nhentai.net/galleries/73130/153.jpg","info":{"width":250,"height":360,"type":"jpg"}},{"link":"https://i.nhentai.net/galleries/73130/154.jpg","info":{"width":250,"height":360,"type":"jpg"}},{"link":"https://i.nhentai.net/galleries/73130/155.jpg","info":{"width":250,"height":360,"type":"jpg"}},{"link":"https://i.nhentai.net/galleries/73130/156.jpg","info":{"width":250,"height":360,"type":"jpg"}},{"link":"https://i.nhentai.net/galleries/73130/157.jpg","info":{"width":250,"height":360,"type":"jpg"}},{"link":"https://i.nhentai.net/galleries/73130/158.jpg","info":{"width":250,"height":360,"type":"jpg"}},{"link":"https://i.nhentai.net/galleries/73130/159.jpg","info":{"width":250,"height":360,"type":"jpg"}},{"link":"https://i.nhentai.net/galleries/73130/160.jpg","info":{"width":250,"height":360,"type":"jpg"}},{"link":"https://i.nhentai.net/galleries/73130/161.jpg","info":{"width":250,"height":360,"type":"jpg"}},{"link":"https://i.nhentai.net/galleries/73130/162.jpg","info":{"width":250,"height":360,"type":"jpg"}},{"link":"https://i.nhentai.net/galleries/73130/163.jpg","info":{"width":250,"height":360,"type":"jpg"}},{"link":"https://i.nhentai.net/galleries/73130/164.jpg","info":{"width":250,"height":360,"type":"jpg"}},{"link":"https://i.nhentai.net/galleries/73130/165.jpg","info":{"width":250,"height":360,"type":"jpg"}},{"link":"https://i.nhentai.net/galleries/73130/166.jpg","info":{"width":250,"height":360,"type":"jpg"}},{"link":"https://i.nhentai.net/galleries/73130/167.jpg","info":{"width":250,"height":360,"type":"jpg"}},{"link":"https://i.nhentai.net/galleries/73130/168.jpg","info":{"width":250,"height":360,"type":"jpg"}},{"link":"https://i.nhentai.net/galleries/73130/169.jpg","info":{"width":250,"height":360,"type":"jpg"}},{"link":"https://i.nhentai.net/galleries/73130/170.jpg","info":{"width":250,"height":360,"type":"jpg"}},{"link":"https://i.nhentai.net/galleries/73130/171.jpg","info":{"width":250,"height":360,"type":"jpg"}},{"link":"https://i.nhentai.net/galleries/73130/172.jpg","info":{"width":250,"height":360,"type":"jpg"}},{"link":"https://i.nhentai.net/galleries/73130/173.jpg","info":{"width":250,"height":360,"type":"jpg"}},{"link":"https://i.nhentai.net/galleries/73130/174.jpg","info":{"width":250,"height":360,"type":"jpg"}},{"link":"https://i.nhentai.net/galleries/73130/175.jpg","info":{"width":250,"height":360,"type":"jpg"}},{"link":"https://i.nhentai.net/galleries/73130/176.jpg","info":{"width":250,"height":360,"type":"jpg"}},{"link":"https://i.nhentai.net/galleries/73130/177.jpg","info":{"width":250,"height":360,"type":"jpg"}},{"link":"https://i.nhentai.net/galleries/73130/178.jpg","info":{"width":250,"height":360,"type":"jpg"}},{"link":"https://i.nhentai.net/galleries/73130/179.jpg","info":{"width":250,"height":360,"type":"jpg"}},{"link":"https://i.nhentai.net/galleries/73130/180.jpg","info":{"width":250,"height":360,"type":"jpg"}},{"link":"https://i.nhentai.net/galleries/73130/181.jpg","info":{"width":250,"height":360,"type":"jpg"}},{"link":"https://i.nhentai.net/galleries/73130/182.jpg","info":{"width":250,"height":360,"type":"jpg"}},{"link":"https://i.nhentai.net/galleries/73130/183.jpg","info":{"width":250,"height":360,"type":"jpg"}},{"link":"https://i.nhentai.net/galleries/73130/184.jpg","info":{"width":250,"height":360,"type":"jpg"}},{"link":"https://i.nhentai.net/galleries/73130/185.jpg","info":{"width":250,"height":360,"type":"jpg"}},{"link":"https://i.nhentai.net/galleries/73130/186.jpg","info":{"width":250,"height":360,"type":"jpg"}},{"link":"https://i.nhentai.net/galleries/73130/187.jpg","info":{"width":250,"height":360,"type":"jpg"}},{"link":"https://i.nhentai.net/galleries/73130/188.jpg","info":{"width":250,"height":360,"type":"jpg"}},{"link":"https://i.nhentai.net/galleries/73130/189.jpg","info":{"width":250,"height":360,"type":"jpg"}}]},"info":{"amount":189,"mediaId":73130,"upload":1403985305},"metadata":{"artists":["iwabuchi piroshi"],"categories":["manga"],"characters":[],"groups":[],"language":"japanese","parodies":[],"tags":["maid","femdom","bondage","wooden horse","yuri","tankoubon","uncensored"]}}