{"id":217583,"title":{"english":"(Reitaisai 14) [Mousouzoku no Soukutsu (Akasode)] Ningyohime no Tawamure (Touhou Project)","japanese":"(例大祭14) [妄想族の巣窟 (赤袖)] 人魚姫の戯れ (東方Project)","display":"Ningyohime no Tawamure"},"images":{"cover":{"link":"https://i.nhentai.net/galleries/1157079/cover.jpg","info":{"width":350,"height":497,"type":"jpg"}},"thumbnail":{"link":"https://i.nhentai.net/galleries/1157079/cover.jpg","info":{"width":250,"height":355,"type":"jpg"}},"pages":[{"link":"https://i.nhentai.net/galleries/1157079/1.jpg","info":{"width":250,"height":355,"type":"jpg"}},{"link":"https://i.nhentai.net/galleries/1157079/2.jpg","info":{"width":250,"height":355,"type":"jpg"}},{"link":"https://i.nhentai.net/galleries/1157079/3.jpg","info":{"width":250,"height":355,"type":"jpg"}},{"link":"https://i.nhentai.net/galleries/1157079/4.jpg","info":{"width":250,"height":355,"type":"jpg"}},{"link":"https://i.nhentai.net/galleries/1157079/5.jpg","info":{"width":250,"height":355,"type":"jpg"}},{"link":"https://i.nhentai.net/galleries/1157079/6.jpg","info":{"width":250,"height":355,"type":"jpg"}},{"link":"https://i.nhentai.net/galleries/1157079/7.jpg","info":{"width":250,"height":355,"type":"jpg"}},{"link":"https://i.nhentai.net/galleries/1157079/8.jpg","info":{"width":250,"height":355,"type":"jpg"}},{"link":"https://i.nhentai.net/galleries/1157079/9.jpg","info":{"width":250,"height":355,"type":"jpg"}},{"link":"https://i.nhentai.net/galleries/1157079/10.jpg","info":{"width":250,"height":355,"type":"jpg"}},{"link":"https://i.nhentai.net/galleries/1157079/11.jpg","info":{"width":250,"height":355,"type":"jpg"}},{"link":"https://i.nhentai.net/galleries/1157079/12.jpg","info":{"width":250,"height":355,"type":"jpg"}},{"link":"https://i.nhentai.net/galleries/1157079/13.jpg","info":{"width":250,"height":355,"type":"jpg"}},{"link":"https://i.nhentai.net/galleries/1157079/14.jpg","info":{"width":250,"height":355,"type":"jpg"}},{"link":"https://i.nhentai.net/galleries/1157079/15.jpg","info":{"width":250,"height":355,"type":"jpg"}},{"link":"https://i.nhentai.net/galleries/1157079/16.jpg","info":{"width":250,"height":355,"type":"jpg"}},{"link":"https://i.nhentai.net/galleries/1157079/17.jpg","info":{"width":250,"height":355,"type":"jpg"}},{"link":"https://i.nhentai.net/galleries/1157079/18.jpg","info":{"width":250,"height":355,"type":"jpg"}}]},"info":{"amount":18,"mediaId":1157079},"metadata":{"artists":[{"name":"akasode","count":15}],"categories":[{"name":"doujinshi","count":228729}],"characters":[{"name":"wakasagihime","count":41}],"groups":[{"name":"mousouzoku no soukutsu","count":14}],"language":"japanese","parodies":[{"name":"touhou project","count":16177}],"tags":[{"name":"full censorship","count":17000},{"name":"full color","count":33404},{"name":"big breasts","count":103273},{"name":"mermaid","count":306},{"name":"monster girl","count":3332},{"name":"sole female","count":66202},{"name":"shotacon","count":39737},{"name":"sole male","count":60070}]}}