{"id":359737,"title":{"english":"(C91) [Inu to Kotatsu (Nanase Mizuho)] Inu to Kotatsu C91 Omake (Granblue Fantasy)","japanese":"(C91) [犬とコタツ (七瀬瑞穂)] 犬とコタツ C91おまけ (グランブルーファンタジー)","display":"Inu to Kotatsu C91 Omake"},"images":{"cover":{"link":"https://i.nhentai.net/galleries/1914556/cover.jpg","info":{"width":350,"height":502,"type":"jpg"}},"thumbnail":{"link":"https://i.nhentai.net/galleries/1914556/cover.jpg","info":{"width":250,"height":359,"type":"jpg"}},"pages":[{"link":"https://i.nhentai.net/galleries/1914556/1.jpg","info":{"width":250,"height":359,"type":"jpg"}},{"link":"https://i.nhentai.net/galleries/1914556/2.jpg","info":{"width":250,"height":359,"type":"jpg"}},{"link":"https://i.nhentai.net/galleries/1914556/3.jpg","info":{"width":250,"height":359,"type":"jpg"}},{"link":"https://i.nhentai.net/galleries/1914556/4.jpg","info":{"width":250,"height":359,"type":"jpg"}}]},"info":{"amount":4,"mediaId":1914556},"metadata":{"artists":[{"name":"nanase mizuho","count":278}],"categories":[{"name":"doujinshi","count":269742}],"characters":[{"name":"alicia","count":46}],"groups":[{"name":"inu to kotatsu","count":42}],"language":"japanese","parodies":[{"name":"granblue fantasy","count":3371}],"tags":[{"name":"handjob","count":7736},{"name":"big breasts","count":123663},{"name":"stockings","count":75753},{"name":"horns","count":3908},{"name":"gloves","count":4956}]}}