{"id":363050,"title":{"english":"[Puripuri JET] Nyan Nyan Ghislaine no Bouken | Nyan Nyan Ghislaine's Adventure (Mushoku Tensei ~Isekai Ittara Honki Dasu~) [English] {Doujins.com}","japanese":"[プリプリJET] にゃんにゃんギレーヌの冒険 (無職転生 ～異世界行ったら本気だす～) [英訳]","display":"Nyan Nyan Ghislaine no Bouken | Nyan Nyan Ghislaine's Adventure"},"images":{"cover":{"link":"https://t.nhentai.net/galleries/1936017/cover.jpg","info":{"width":350,"height":184,"type":"jpg"}},"thumbnail":{"link":"https://t.nhentai.net/galleries/1936017/1t.jpg","info":{"width":250,"height":131,"type":"jpg"}},"pages":[{"link":"https://i.nhentai.net/galleries/1936017/1.jpg","info":{"width":250,"height":131,"type":"jpg"}},{"link":"https://i.nhentai.net/galleries/1936017/2.jpg","info":{"width":250,"height":131,"type":"jpg"}},{"link":"https://i.nhentai.net/galleries/1936017/3.jpg","info":{"width":250,"height":131,"type":"jpg"}},{"link":"https://i.nhentai.net/galleries/1936017/4.jpg","info":{"width":250,"height":131,"type":"jpg"}},{"link":"https://i.nhentai.net/galleries/1936017/5.jpg","info":{"width":250,"height":131,"type":"jpg"}},{"link":"https://i.nhentai.net/galleries/1936017/6.jpg","info":{"width":250,"height":131,"type":"jpg"}}]},"info":{"amount":6,"mediaId":1936017,"upload":1623907816},"metadata":{"artists":["puripuri jet"],"categories":["doujinshi"],"characters":["ghislaine dedoldia"],"groups":[],"language":"translated","parodies":["mushoku tensei"],"tags":["big breasts","dark skin","eyepatch","kemonomimi","rape","scar","sole female","group"]}}