{"id":401986,"title":{"english":"[Neyuki Rei] Otoge-san Book 2","japanese":"[メイの天使 (根雪れい)] 大峠さんがヒルクライムしようとしている。 [DL版]","display":"Otoge-san Book 2"},"images":{"cover":{"link":"https://t.nhentai.net/galleries/2212786/cover.jpg","info":{"width":350,"height":247,"type":"jpg"}},"thumbnail":{"link":"https://t.nhentai.net/galleries/2212786/1t.jpg","info":{"width":250,"height":176,"type":"jpg"}},"pages":[{"link":"https://i.nhentai.net/galleries/2212786/1.jpg","info":{"width":250,"height":176,"type":"jpg"}},{"link":"https://i.nhentai.net/galleries/2212786/2.jpg","info":{"width":250,"height":176,"type":"jpg"}},{"link":"https://i.nhentai.net/galleries/2212786/3.jpg","info":{"width":250,"height":176,"type":"jpg"}},{"link":"https://i.nhentai.net/galleries/2212786/4.jpg","info":{"width":250,"height":176,"type":"jpg"}},{"link":"https://i.nhentai.net/galleries/2212786/5.jpg","info":{"width":250,"height":176,"type":"jpg"}},{"link":"https://i.nhentai.net/galleries/2212786/6.jpg","info":{"width":250,"height":176,"type":"jpg"}},{"link":"https://i.nhentai.net/galleries/2212786/7.jpg","info":{"width":250,"height":176,"type":"jpg"}},{"link":"https://i.nhentai.net/galleries/2212786/8.jpg","info":{"width":250,"height":176,"type":"jpg"}},{"link":"https://i.nhentai.net/galleries/2212786/9.jpg","info":{"width":250,"height":176,"type":"jpg"}},{"link":"https://i.nhentai.net/galleries/2212786/10.jpg","info":{"width":250,"height":176,"type":"jpg"}},{"link":"https://i.nhentai.net/galleries/2212786/11.jpg","info":{"width":250,"height":176,"type":"jpg"}},{"link":"https://i.nhentai.net/galleries/2212786/12.jpg","info":{"width":250,"height":176,"type":"jpg"}},{"link":"https://i.nhentai.net/galleries/2212786/13.jpg","info":{"width":250,"height":176,"type":"jpg"}},{"link":"https://i.nhentai.net/galleries/2212786/14.jpg","info":{"width":250,"height":176,"type":"jpg"}},{"link":"https://i.nhentai.net/galleries/2212786/15.jpg","info":{"width":250,"height":176,"type":"jpg"}},{"link":"https://i.nhentai.net/galleries/2212786/16.jpg","info":{"width":250,"height":176,"type":"jpg"}},{"link":"https://i.nhentai.net/galleries/2212786/17.jpg","info":{"width":250,"height":176,"type":"jpg"}},{"link":"https://i.nhentai.net/galleries/2212786/18.jpg","info":{"width":250,"height":176,"type":"jpg"}},{"link":"https://i.nhentai.net/galleries/2212786/19.jpg","info":{"width":250,"height":176,"type":"jpg"}},{"link":"https://i.nhentai.net/galleries/2212786/20.jpg","info":{"width":250,"height":176,"type":"jpg"}},{"link":"https://i.nhentai.net/galleries/2212786/21.jpg","info":{"width":250,"height":176,"type":"jpg"}},{"link":"https://i.nhentai.net/galleries/2212786/22.jpg","info":{"width":250,"height":176,"type":"jpg"}},{"link":"https://i.nhentai.net/galleries/2212786/23.jpg","info":{"width":250,"height":176,"type":"jpg"}},{"link":"https://i.nhentai.net/galleries/2212786/24.jpg","info":{"width":250,"height":176,"type":"jpg"}},{"link":"https://i.nhentai.net/galleries/2212786/25.jpg","info":{"width":250,"height":176,"type":"jpg"}},{"link":"https://i.nhentai.net/galleries/2212786/26.jpg","info":{"width":250,"height":176,"type":"jpg"}},{"link":"https://i.nhentai.net/galleries/2212786/27.jpg","info":{"width":250,"height":176,"type":"jpg"}},{"link":"https://i.nhentai.net/galleries/2212786/28.jpg","info":{"width":250,"height":176,"type":"jpg"}},{"link":"https://i.nhentai.net/galleries/2212786/29.jpg","info":{"width":250,"height":176,"type":"jpg"}},{"link":"https://i.nhentai.net/galleries/2212786/30.jpg","info":{"width":250,"height":176,"type":"jpg"}}]},"info":{"amount":30,"mediaId":2212786,"upload":1651820831},"metadata":{"artists":["neyuki rei"],"categories":["doujinshi"],"characters":[],"groups":["may no tenshi"],"language":"japanese","parodies":["original"],"tags":["bbw","glasses","thick eyebrows"]}}