{"id":92266,"title":{"english":"(C82) [PRETTY☆MAIDS (Itou Hiromine)] Nakata Whip (Amagami)","japanese":"(C82) [PRETTY☆MAIDS (伊東宏峰)] 中多ホイップ (アマガミ)","display":"Nakata Whip"},"images":{"cover":{"link":"https://t.nhentai.net/galleries/595867/cover.jpg","info":{"width":350,"height":494,"type":"jpg"}},"thumbnail":{"link":"https://t.nhentai.net/galleries/595867/1t.jpg","info":{"width":250,"height":353,"type":"jpg"}},"pages":[{"link":"https://i.nhentai.net/galleries/595867/1.jpg","info":{"width":250,"height":353,"type":"jpg"}},{"link":"https://i.nhentai.net/galleries/595867/2.jpg","info":{"width":250,"height":353,"type":"jpg"}},{"link":"https://i.nhentai.net/galleries/595867/3.jpg","info":{"width":250,"height":353,"type":"jpg"}},{"link":"https://i.nhentai.net/galleries/595867/4.jpg","info":{"width":250,"height":353,"type":"jpg"}},{"link":"https://i.nhentai.net/galleries/595867/5.jpg","info":{"width":250,"height":353,"type":"jpg"}},{"link":"https://i.nhentai.net/galleries/595867/6.jpg","info":{"width":250,"height":353,"type":"jpg"}},{"link":"https://i.nhentai.net/galleries/595867/7.jpg","info":{"width":250,"height":353,"type":"jpg"}},{"link":"https://i.nhentai.net/galleries/595867/8.jpg","info":{"width":250,"height":353,"type":"jpg"}},{"link":"https://i.nhentai.net/galleries/595867/9.jpg","info":{"width":250,"height":353,"type":"jpg"}},{"link":"https://i.nhentai.net/galleries/595867/10.jpg","info":{"width":250,"height":353,"type":"jpg"}},{"link":"https://i.nhentai.net/galleries/595867/11.jpg","info":{"width":250,"height":353,"type":"jpg"}},{"link":"https://i.nhentai.net/galleries/595867/12.jpg","info":{"width":250,"height":353,"type":"jpg"}},{"link":"https://i.nhentai.net/galleries/595867/13.jpg","info":{"width":250,"height":353,"type":"jpg"}},{"link":"https://i.nhentai.net/galleries/595867/14.jpg","info":{"width":250,"height":353,"type":"jpg"}},{"link":"https://i.nhentai.net/galleries/595867/15.jpg","info":{"width":250,"height":353,"type":"jpg"}},{"link":"https://i.nhentai.net/galleries/595867/16.jpg","info":{"width":250,"height":353,"type":"jpg"}},{"link":"https://i.nhentai.net/galleries/595867/17.jpg","info":{"width":250,"height":353,"type":"jpg"}},{"link":"https://i.nhentai.net/galleries/595867/18.jpg","info":{"width":250,"height":353,"type":"jpg"}},{"link":"https://i.nhentai.net/galleries/595867/19.jpg","info":{"width":250,"height":353,"type":"jpg"}},{"link":"https://i.nhentai.net/galleries/595867/20.jpg","info":{"width":250,"height":353,"type":"jpg"}},{"link":"https://i.nhentai.net/galleries/595867/21.jpg","info":{"width":250,"height":353,"type":"jpg"}},{"link":"https://i.nhentai.net/galleries/595867/22.jpg","info":{"width":250,"height":353,"type":"jpg"}}]},"info":{"amount":22,"mediaId":595867,"upload":1403999003},"metadata":{"artists":["itou hiromine"],"categories":["doujinshi"],"characters":["junichi tachibana","sae nakata"],"groups":["pretty maids"],"language":"japanese","parodies":["amagami"],"tags":["big breasts","exhibitionism","stockings","waitress","school swimsuit","schoolgirl uniform","schoolboy uniform"]}}